apk_builder/__init__.py
apk_builder/core.py
website_to_apk_converter-0.1.0.dist-info/METADATA
website_to_apk_converter-0.1.0.dist-info/WHEEL
website_to_apk_converter-0.1.0.dist-info/top_level.txt
website_to_apk_converter-0.1.0.dist-info/RECORD
