Metadata-Version: 2.4
Name: website-to-apk-converter
Version: 0.1.0
Summary: A library to convert websites into Android APK files using android sdk and APKTool.
Author: SHAIK JANU
Author-email: shaiksadikjanu@gmail.com
Classifier: Programming Language :: Python :: 3
Classifier: License :: OSI Approved :: MIT License
Classifier: Operating System :: OS Independent
Requires-Python: >=3.6
Requires-Dist: Pillow
Dynamic: author
Dynamic: author-email
Dynamic: classifier
Dynamic: description
Dynamic: description-content-type
Dynamic: requires-dist
Dynamic: requires-python
Dynamic: summary
